toyblock/__init__.py
toyblock-2.0.0.dist-info/DESCRIPTION.rst
toyblock-2.0.0.dist-info/METADATA
toyblock-2.0.0.dist-info/RECORD
toyblock-2.0.0.dist-info/WHEEL
toyblock-2.0.0.dist-info/metadata.json
toyblock-2.0.0.dist-info/top_level.txt
