Metadata-Version: 2.0
Name: toyblock
Version: 2.0.0
Summary: A pythonic and fast Entity-Component-System written in pure Python
Home-page: https://github.com/dotoscat/toyblock
Author: Oscar Triano 'dotoscat'
Author-email: UNKNOWN
License: LGPL-3.0
Keywords: development videogame gamedev
Platform: UNKNOWN
Classifier: Development Status :: 5 - Production/Stable
Classifier: Intended Audience :: Developers
Classifier: License :: OSI Approved :: GNU General Public License v3 (GPLv3)
Classifier: License :: OSI Approved :: GNU General Public License v3 or later (GPLv3+)
